kokex/__init__.py
kokex/api.py
kokex/core/__init__.py
kokex/core/parser.py
kokex/core/preproc.py
kokex/core/tree.py
kokex-0.0.11.dist-info/LICENSE
kokex-0.0.11.dist-info/METADATA
kokex-0.0.11.dist-info/WHEEL
kokex-0.0.11.dist-info/top_level.txt
kokex-0.0.11.dist-info/RECORD
