Metadata-Version: 2.1
Name: kokex
Version: 0.0.11
Summary: A Korean Keywords Extractor with Syntactic Analysis
Home-page: https://github.com/jsmyung-datansoft/kokex
Author: jsmyung
Author-email: jsmyung@datansoft.com
License: UNKNOWN
Platform: UNKNOWN
Classifier: Programming Language :: Python :: 3
Classifier: License :: OSI Approved :: MIT License
Classifier: Operating System :: OS Independent
Requires-Python: >=3.7
Requires-Dist: konlpy (>=0.5.2)
Requires-Dist: networkx (>=2.5.1)
